{
  "id": "feature_1764930324.197958",
  "name": "Auto-Creation of Compliance Records - Back Office User",
  "description": "Compliance records are automatically created via API integration when new compliance entries are created in Focus system, with auto-populated fields that cannot be manually edited",
  "created_at": "2025-12-05T15:55:24.197958",
  "updated_at": "2025-12-05T15:55:26.900197",
  "project_id": "ce1a8cc0-da85-48e2-b349-7bf9311e023f",
  "background": [
    {
      "keyword": "Given",
      "text": "I am on the application"
    },
    {
      "keyword": "And",
      "text": "I am logged in as a Back Office User"
    },
    {
      "keyword": "And",
      "text": "the Focus system API integration is active"
    }
  ],
  "scenarios": [
    {
      "name": "Compliance record automatically created from Focus system",
      "tags": [
        "@smoke",
        "@positive"
      ],
      "description": null,
      "steps": [
        {
          "keyword": "Given",
          "text": "a new compliance record is created in the Focus system"
        },
        {
          "keyword": "When",
          "text": "the API integration processes the new record"
        },
        {
          "keyword": "Then",
          "text": "a compliance record should be automatically created"
        },
        {
          "keyword": "And",
          "text": "the record should appear in the Compliance Dashboard list view"
        },
        {
          "keyword": "And",
          "text": "the Overall Status should be set to \"non-compliant\""
        }
      ]
    },
    {
      "name": "Auto-populated fields are correctly fetched from Focus",
      "tags": [
        "@positive",
        "@integration"
      ],
      "description": null,
      "steps": [
        {
          "keyword": "Given",
          "text": "a new compliance record exists in Focus with complete data"
        },
        {
          "keyword": "When",
          "text": "the record is automatically created via API"
        },
        {
          "keyword": "Then",
          "text": "the \"First Name\" field should be populated from Focus"
        },
        {
          "keyword": "And",
          "text": "the \"Last Name\" field should be populated from Focus"
        },
        {
          "keyword": "And",
          "text": "the \"Email ID\" field should be populated from Focus"
        },
        {
          "keyword": "And",
          "text": "the COI attachments should be imported from the Attachments Tab"
        }
      ]
    },
    {
      "name": "Auto-populated fields cannot be manually edited",
      "tags": [
        "@positive",
        "@validation"
      ],
      "description": null,
      "steps": [
        {
          "keyword": "Given",
          "text": "I am viewing an auto-created compliance record"
        },
        {
          "keyword": "When",
          "text": "I attempt to edit the \"First Name\" field"
        },
        {
          "keyword": "Then",
          "text": "the field should be read-only"
        },
        {
          "keyword": "And",
          "text": "the \"Last Name\" field should be read-only"
        },
        {
          "keyword": "And",
          "text": "the \"Email ID\" field should be read-only"
        },
        {
          "keyword": "And",
          "text": "the auto-imported attachments should not be editable"
        }
      ]
    },
    {
      "name": "Back Office user can edit requirements and attachments",
      "tags": [
        "@positive",
        "@editing"
      ],
      "description": null,
      "steps": [
        {
          "keyword": "Given",
          "text": "I am viewing an auto-created compliance record"
        },
        {
          "keyword": "When",
          "text": "I update the requirements section"
        },
        {
          "keyword": "And",
          "text": "I add additional attachments"
        },
        {
          "keyword": "And",
          "text": "I click the \"Save\" button"
        },
        {
          "keyword": "Then",
          "text": "the requirements should be updated successfully"
        },
        {
          "keyword": "And",
          "text": "the new attachments should be saved"
        },
        {
          "keyword": "And",
          "text": "the auto-populated fields should remain unchanged"
        }
      ]
    },
    {
      "name": "Default non-compliant status can be updated after review",
      "tags": [
        "@positive",
        "@status"
      ],
      "description": null,
      "steps": [
        {
          "keyword": "Given",
          "text": "I am viewing an auto-created compliance record with \"non-compliant\" status"
        },
        {
          "keyword": "When",
          "text": "I review the requirements and attachments"
        },
        {
          "keyword": "And",
          "text": "I change the Overall Status to \"compliant\""
        },
        {
          "keyword": "And",
          "text": "I click the \"Save\" button"
        },
        {
          "keyword": "Then",
          "text": "the status should be updated to \"compliant\""
        },
        {
          "keyword": "And",
          "text": "the changes should be reflected in the Compliance Dashboard"
        }
      ]
    },
    {
      "name": "Auto-created record appears in Compliance Dashboard list view",
      "tags": [
        "@positive",
        "@dashboard"
      ],
      "description": null,
      "steps": [
        {
          "keyword": "Given",
          "text": "multiple compliance records have been auto-created from Focus"
        },
        {
          "keyword": "When",
          "text": "I navigate to the Compliance Dashboard"
        },
        {
          "keyword": "Then",
          "text": "I should see all auto-created records in the list view"
        },
        {
          "keyword": "And",
          "text": "each record should display the auto-populated names and email"
        },
        {
          "keyword": "And",
          "text": "the default status should show as \"non-compliant\""
        }
      ]
    },
    {
      "name": "Manual creation of compliance records is not allowed",
      "tags": [
        "@negative",
        "@validation"
      ],
      "description": null,
      "steps": [
        {
          "keyword": "Given",
          "text": "I am on the Compliance Dashboard"
        },
        {
          "keyword": "When",
          "text": "I look for options to manually create a new compliance record"
        },
        {
          "keyword": "Then",
          "text": "no \"Create New\" or \"Add Record\" button should be available"
        },
        {
          "keyword": "And",
          "text": "manual creation functionality should not be accessible through the front end"
        }
      ]
    },
    {
      "name": "API integration failure prevents record creation",
      "tags": [
        "@negative",
        "@integration"
      ],
      "description": null,
      "steps": [
        {
          "keyword": "Given",
          "text": "the Focus system API integration is temporarily unavailable"
        },
        {
          "keyword": "When",
          "text": "a new compliance record is created in Focus"
        },
        {
          "keyword": "Then",
          "text": "the record should not be created in the system"
        },
        {
          "keyword": "And",
          "text": "an error should be logged for the failed integration"
        },
        {
          "keyword": "And",
          "text": "the record should not appear in the Compliance Dashboard"
        }
      ]
    },
    {
      "name": "Incomplete data from Focus system handling",
      "tags": [
        "@negative",
        "@data-validation"
      ],
      "description": null,
      "steps": [
        {
          "keyword": "Given",
          "text": "a compliance record in Focus has missing required fields"
        },
        {
          "keyword": "When",
          "text": "the API attempts to create the record automatically"
        },
        {
          "keyword": "Then",
          "text": "the system should handle the incomplete data gracefully"
        },
        {
          "keyword": "And",
          "text": "an error notification should be generated"
        },
        {
          "keyword": "And",
          "text": "the incomplete record should not appear in the dashboard"
        }
      ]
    },
    {
      "name": "Attempting to delete auto-populated attachments fails",
      "tags": [
        "@negative",
        "@attachment"
      ],
      "description": null,
      "steps": [
        {
          "keyword": "Given",
          "text": "I am viewing an auto-created compliance record with COI attachments"
        },
        {
          "keyword": "When",
          "text": "I attempt to delete the auto-imported COI attachment"
        },
        {
          "keyword": "Then",
          "text": "the deletion should be prevented"
        },
        {
          "keyword": "And",
          "text": "an error message should indicate the attachment cannot be removed"
        },
        {
          "keyword": "And",
          "text": "the attachment should remain in the record"
        }
      ]
    },
    {
      "name": "Large volume of Focus records processed correctly",
      "tags": [
        "@edge-case",
        "@performance"
      ],
      "description": null,
      "steps": [
        {
          "keyword": "Given",
          "text": "multiple compliance records are created simultaneously in Focus"
        },
        {
          "keyword": "When",
          "text": "the API processes all records in batch"
        },
        {
          "keyword": "Then",
          "text": "all records should be created successfully"
        },
        {
          "keyword": "And",
          "text": "each record should maintain data integrity"
        },
        {
          "keyword": "And",
          "text": "the Compliance Dashboard should display all records"
        }
      ]
    },
    {
      "name": "Focus record with maximum allowed attachments",
      "tags": [
        "@edge-case",
        "@boundary"
      ],
      "description": null,
      "steps": [
        {
          "keyword": "Given",
          "text": "a Focus compliance record has the maximum number of allowed attachments"
        },
        {
          "keyword": "When",
          "text": "the record is auto-created via API"
        },
        {
          "keyword": "Then",
          "text": "all attachments should be imported successfully"
        },
        {
          "keyword": "And",
          "text": "the system should handle the maximum attachment limit"
        },
        {
          "keyword": "And",
          "text": "the record should be created without errors"
        }
      ]
    },
    {
      "name": "Duplicate compliance record prevention",
      "tags": [
        "@edge-case",
        "@duplicate"
      ],
      "description": null,
      "steps": [
        {
          "keyword": "Given",
          "text": "a compliance record already exists from a previous Focus integration"
        },
        {
          "keyword": "When",
          "text": "the same record is sent again through the API"
        },
        {
          "keyword": "Then",
          "text": "the system should detect the duplicate"
        },
        {
          "keyword": "And",
          "text": "no duplicate record should be created"
        },
        {
          "keyword": "And",
          "text": "the existing record should remain unchanged"
        }
      ]
    },
    {
      "name": "Alternative workflow through dashboard filtering",
      "tags": [
        "@alternative",
        "@workflow"
      ],
      "description": null,
      "steps": [
        {
          "keyword": "Given",
          "text": "multiple auto-created compliance records exist with different statuses"
        },
        {
          "keyword": "When",
          "text": "I filter the dashboard by \"non-compliant\" status"
        },
        {
          "keyword": "And",
          "text": "I select multiple records for bulk status update"
        },
        {
          "keyword": "Then",
          "text": "I should be able to update multiple records simultaneously"
        },
        {
          "keyword": "And",
          "text": "the filtered view should update to reflect the changes"
        }
      ]
    }
  ],
  "gherkin_content": "Feature: Auto-Creation of Compliance Records - Back Office User\n  Compliance records are automatically created via API integration when new compliance entries are created in Focus system, with auto-populated fields that cannot be manually edited\n\n  Background:\n    Given I am on the application\n    And I am logged in as a Back Office User\n    And the Focus system API integration is active\n\n  @smoke @positive\n  Scenario: Compliance record automatically created from Focus system\n    Given a new compliance record is created in the Focus system\n    When the API integration processes the new record\n    Then a compliance record should be automatically created\n    And the record should appear in the Compliance Dashboard list view\n    And the Overall Status should be set to \"non-compliant\"\n\n  @positive @integration\n  Scenario: Auto-populated fields are correctly fetched from Focus\n    Given a new compliance record exists in Focus with complete data\n    When the record is automatically created via API\n    Then the \"First Name\" field should be populated from Focus\n    And the \"Last Name\" field should be populated from Focus\n    And the \"Email ID\" field should be populated from Focus\n    And the COI attachments should be imported from the Attachments Tab\n\n  @positive @validation\n  Scenario: Auto-populated fields cannot be manually edited\n    Given I am viewing an auto-created compliance record\n    When I attempt to edit the \"First Name\" field\n    Then the field should be read-only\n    And the \"Last Name\" field should be read-only\n    And the \"Email ID\" field should be read-only\n    And the auto-imported attachments should not be editable\n\n  @positive @editing\n  Scenario: Back Office user can edit requirements and attachments\n    Given I am viewing an auto-created compliance record\n    When I update the requirements section\n    And I add additional attachments\n    And I click the \"Save\" button\n    Then the requirements should be updated successfully\n    And the new attachments should be saved\n    And the auto-populated fields should remain unchanged\n\n  @positive @status\n  Scenario: Default non-compliant status can be updated after review\n    Given I am viewing an auto-created compliance record with \"non-compliant\" status\n    When I review the requirements and attachments\n    And I change the Overall Status to \"compliant\"\n    And I click the \"Save\" button\n    Then the status should be updated to \"compliant\"\n    And the changes should be reflected in the Compliance Dashboard\n\n  @positive @dashboard\n  Scenario: Auto-created record appears in Compliance Dashboard list view\n    Given multiple compliance records have been auto-created from Focus\n    When I navigate to the Compliance Dashboard\n    Then I should see all auto-created records in the list view\n    And each record should display the auto-populated names and email\n    And the default status should show as \"non-compliant\"\n\n  @negative @validation\n  Scenario: Manual creation of compliance records is not allowed\n    Given I am on the Compliance Dashboard\n    When I look for options to manually create a new compliance record\n    Then no \"Create New\" or \"Add Record\" button should be available\n    And manual creation functionality should not be accessible through the front end\n\n  @negative @integration\n  Scenario: API integration failure prevents record creation\n    Given the Focus system API integration is temporarily unavailable\n    When a new compliance record is created in Focus\n    Then the record should not be created in the system\n    And an error should be logged for the failed integration\n    And the record should not appear in the Compliance Dashboard\n\n  @negative @data-validation\n  Scenario: Incomplete data from Focus system handling\n    Given a compliance record in Focus has missing required fields\n    When the API attempts to create the record automatically\n    Then the system should handle the incomplete data gracefully\n    And an error notification should be generated\n    And the incomplete record should not appear in the dashboard\n\n  @negative @attachment\n  Scenario: Attempting to delete auto-populated attachments fails\n    Given I am viewing an auto-created compliance record with COI attachments\n    When I attempt to delete the auto-imported COI attachment\n    Then the deletion should be prevented\n    And an error message should indicate the attachment cannot be removed\n    And the attachment should remain in the record\n\n  @edge-case @performance\n  Scenario: Large volume of Focus records processed correctly\n    Given multiple compliance records are created simultaneously in Focus\n    When the API processes all records in batch\n    Then all records should be created successfully\n    And each record should maintain data integrity\n    And the Compliance Dashboard should display all records\n\n  @edge-case @boundary\n  Scenario: Focus record with maximum allowed attachments\n    Given a Focus compliance record has the maximum number of allowed attachments\n    When the record is auto-created via API\n    Then all attachments should be imported successfully\n    And the system should handle the maximum attachment limit\n    And the record should be created without errors\n\n  @edge-case @duplicate\n  Scenario: Duplicate compliance record prevention\n    Given a compliance record already exists from a previous Focus integration\n    When the same record is sent again through the API\n    Then the system should detect the duplicate\n    And no duplicate record should be created\n    And the existing record should remain unchanged\n\n  @alternative @workflow\n  Scenario: Alternative workflow through dashboard filtering\n    Given multiple auto-created compliance records exist with different statuses\n    When I filter the dashboard by \"non-compliant\" status\n    And I select multiple records for bulk status update\n    Then I should be able to update multiple records simultaneously\n    And the filtered view should update to reflect the changes"
}