{
  "id": "feature_1764052939.502135",
  "name": "User Login Authentication",
  "description": "As a user, I want to login to the application so that I can access my dashboard",
  "created_at": "2025-11-25T11:16:05.335238",
  "updated_at": "2025-11-25T12:12:50.024733",
  "project_id": "aeb49f37-436f-4ff2-8785-e84538c377bb",
  "background": [
    {
      "keyword": "Given",
      "text": "I am on the login page"
    },
    {
      "keyword": "And",
      "text": "the login form is displayed"
    }
  ],
  "scenarios": [
    {
      "name": "Successful login with valid email and password",
      "tags": [
        "@smoke",
        "@happy-path",
        "@login"
      ],
      "description": null,
      "steps": [
        {
          "keyword": "Given",
          "text": "I am a registered user with email \"user@example.com\" and password \"Password123\""
        },
        {
          "keyword": "When",
          "text": "I enter \"user@example.com\" in the email field"
        },
        {
          "keyword": "And",
          "text": "I enter \"Password123\" in the password field"
        },
        {
          "keyword": "And",
          "text": "I click the login button"
        },
        {
          "keyword": "Then",
          "text": "I should see the dashboard page"
        },
        {
          "keyword": "And",
          "text": "I should see a welcome message"
        }
      ]
    },
    {
      "name": "Login fails with invalid email",
      "tags": [
        "@negative",
        "@login",
        "@error-handling"
      ],
      "description": null,
      "steps": [
        {
          "keyword": "Given",
          "text": "I am a registered user"
        },
        {
          "keyword": "When",
          "text": "I enter \"invalid@example.com\" in the email field"
        },
        {
          "keyword": "And",
          "text": "I enter \"Password123\" in the password field"
        },
        {
          "keyword": "And",
          "text": "I click the login button"
        },
        {
          "keyword": "Then",
          "text": "I should see an error message"
        },
        {
          "keyword": "And",
          "text": "I should remain on the login page"
        },
        {
          "keyword": "And",
          "text": "the error message should contain \"Invalid credentials\""
        }
      ]
    },
    {
      "name": "Login fails with invalid password",
      "tags": [
        "@negative",
        "@login",
        "@error-handling"
      ],
      "description": null,
      "steps": [
        {
          "keyword": "Given",
          "text": "I am a registered user with email \"user@example.com\""
        },
        {
          "keyword": "When",
          "text": "I enter \"user@example.com\" in the email field"
        },
        {
          "keyword": "And",
          "text": "I enter \"WrongPassword\" in the password field"
        },
        {
          "keyword": "And",
          "text": "I click the login button"
        },
        {
          "keyword": "Then",
          "text": "I should see an error message"
        },
        {
          "keyword": "And",
          "text": "I should remain on the login page"
        },
        {
          "keyword": "And",
          "text": "the error message should contain \"Invalid credentials\""
        }
      ]
    },
    {
      "name": "Login fails with empty email field",
      "tags": [
        "@negative",
        "@ui",
        "@validation"
      ],
      "description": null,
      "steps": [
        {
          "keyword": "Given",
          "text": "I am on the login page"
        },
        {
          "keyword": "When",
          "text": "I leave the email field empty"
        },
        {
          "keyword": "And",
          "text": "I enter \"Password123\" in the password field"
        },
        {
          "keyword": "And",
          "text": "I click the login button"
        },
        {
          "keyword": "Then",
          "text": "I should see a validation error message"
        },
        {
          "keyword": "And",
          "text": "the email field should be highlighted as invalid"
        },
        {
          "keyword": "And",
          "text": "I should remain on the login page"
        }
      ]
    },
    {
      "name": "Login fails with empty password field",
      "tags": [
        "@negative",
        "@ui",
        "@validation"
      ],
      "description": null,
      "steps": [
        {
          "keyword": "Given",
          "text": "I am on the login page"
        },
        {
          "keyword": "When",
          "text": "I enter \"user@example.com\" in the email field"
        },
        {
          "keyword": "And",
          "text": "I leave the password field empty"
        },
        {
          "keyword": "And",
          "text": "I click the login button"
        },
        {
          "keyword": "Then",
          "text": "I should see a validation error message"
        },
        {
          "keyword": "And",
          "text": "the password field should be highlighted as invalid"
        },
        {
          "keyword": "And",
          "text": "I should remain on the login page"
        }
      ]
    },
    {
      "name": "Login fails with both fields empty",
      "tags": [
        "@negative",
        "@edge-case",
        "@validation"
      ],
      "description": null,
      "steps": [
        {
          "keyword": "Given",
          "text": "I am on the login page"
        },
        {
          "keyword": "When",
          "text": "I leave the email field empty"
        },
        {
          "keyword": "And",
          "text": "I leave the password field empty"
        },
        {
          "keyword": "And",
          "text": "I click the login button"
        },
        {
          "keyword": "Then",
          "text": "I should see validation error messages for both fields"
        },
        {
          "keyword": "And",
          "text": "both email and password fields should be highlighted as invalid"
        },
        {
          "keyword": "And",
          "text": "I should remain on the login page"
        }
      ]
    },
    {
      "name": "Login with invalid email format",
      "tags": [
        "@negative",
        "@edge-case",
        "@validation"
      ],
      "description": null,
      "steps": [
        {
          "keyword": "Given",
          "text": "I am on the login page"
        },
        {
          "keyword": "When",
          "text": "I enter \"invalid-email-format\" in the email field"
        },
        {
          "keyword": "And",
          "text": "I enter \"Password123\" in the password field"
        },
        {
          "keyword": "And",
          "text": "I click the login button"
        },
        {
          "keyword": "Then",
          "text": "I should see an email format validation error"
        },
        {
          "keyword": "And",
          "text": "the email field should be highlighted as invalid"
        },
        {
          "keyword": "And",
          "text": "I should remain on the login page"
        }
      ]
    },
    {
      "name": "Password field masks input characters",
      "tags": [
        "@ui",
        "@security"
      ],
      "description": null,
      "steps": [
        {
          "keyword": "Given",
          "text": "I am on the login page"
        },
        {
          "keyword": "When",
          "text": "I enter \"Password123\" in the password field"
        },
        {
          "keyword": "Then",
          "text": "the password field should display masked characters"
        },
        {
          "keyword": "And",
          "text": "the actual password text should not be visible"
        }
      ]
    },
    {
      "name": "Login button is disabled until both fields are filled",
      "tags": [
        "@ui",
        "@edge-case"
      ],
      "description": null,
      "steps": [
        {
          "keyword": "Given",
          "text": "I am on the login page"
        },
        {
          "keyword": "Then",
          "text": "the login button should be disabled"
        },
        {
          "keyword": "When",
          "text": "I enter \"user@example.com\" in the email field"
        },
        {
          "keyword": "Then",
          "text": "the login button should still be disabled"
        },
        {
          "keyword": "When",
          "text": "I enter \"Password123\" in the password field"
        },
        {
          "keyword": "Then",
          "text": "the login button should be enabled"
        }
      ]
    }
  ],
  "gherkin_content": "Feature: User Login Authentication\n  As a user, I want to login to the application so that I can access my dashboard\n\n  Background:\n    StepKeyword.GIVEN I am on the login page\n    StepKeyword.AND the login form is displayed\n\n  @smoke @happy-path @login\n  Scenario: Successful login with valid email and password\n    StepKeyword.GIVEN I am a registered user with email \"user@example.com\" and password \"Password123\"\n    StepKeyword.WHEN I enter \"user@example.com\" in the email field\n    StepKeyword.AND I enter \"Password123\" in the password field\n    StepKeyword.AND I click the login button\n    StepKeyword.THEN I should see the dashboard page\n    StepKeyword.AND I should see a welcome message\n\n  @negative @login @error-handling\n  Scenario: Login fails with invalid email\n    StepKeyword.GIVEN I am a registered user\n    StepKeyword.WHEN I enter \"invalid@example.com\" in the email field\n    StepKeyword.AND I enter \"Password123\" in the password field\n    StepKeyword.AND I click the login button\n    StepKeyword.THEN I should see an error message\n    StepKeyword.AND I should remain on the login page\n    StepKeyword.AND the error message should contain \"Invalid credentials\"\n\n  @negative @login @error-handling\n  Scenario: Login fails with invalid password\n    StepKeyword.GIVEN I am a registered user with email \"user@example.com\"\n    StepKeyword.WHEN I enter \"user@example.com\" in the email field\n    StepKeyword.AND I enter \"WrongPassword\" in the password field\n    StepKeyword.AND I click the login button\n    StepKeyword.THEN I should see an error message\n    StepKeyword.AND I should remain on the login page\n    StepKeyword.AND the error message should contain \"Invalid credentials\"\n\n  @negative @ui @validation\n  Scenario: Login fails with empty email field\n    StepKeyword.GIVEN I am on the login page\n    StepKeyword.WHEN I leave the email field empty\n    StepKeyword.AND I enter \"Password123\" in the password field\n    StepKeyword.AND I click the login button\n    StepKeyword.THEN I should see a validation error message\n    StepKeyword.AND the email field should be highlighted as invalid\n    StepKeyword.AND I should remain on the login page\n\n  @negative @ui @validation\n  Scenario: Login fails with empty password field\n    StepKeyword.GIVEN I am on the login page\n    StepKeyword.WHEN I enter \"user@example.com\" in the email field\n    StepKeyword.AND I leave the password field empty\n    StepKeyword.AND I click the login button\n    StepKeyword.THEN I should see a validation error message\n    StepKeyword.AND the password field should be highlighted as invalid\n    StepKeyword.AND I should remain on the login page\n\n  @negative @edge-case @validation\n  Scenario: Login fails with both fields empty\n    StepKeyword.GIVEN I am on the login page\n    StepKeyword.WHEN I leave the email field empty\n    StepKeyword.AND I leave the password field empty\n    StepKeyword.AND I click the login button\n    StepKeyword.THEN I should see validation error messages for both fields\n    StepKeyword.AND both email and password fields should be highlighted as invalid\n    StepKeyword.AND I should remain on the login page\n\n  @negative @edge-case @validation\n  Scenario: Login with invalid email format\n    StepKeyword.GIVEN I am on the login page\n    StepKeyword.WHEN I enter \"invalid-email-format\" in the email field\n    StepKeyword.AND I enter \"Password123\" in the password field\n    StepKeyword.AND I click the login button\n    StepKeyword.THEN I should see an email format validation error\n    StepKeyword.AND the email field should be highlighted as invalid\n    StepKeyword.AND I should remain on the login page\n\n  @ui @security\n  Scenario: Password field masks input characters\n    StepKeyword.GIVEN I am on the login page\n    StepKeyword.WHEN I enter \"Password123\" in the password field\n    StepKeyword.THEN the password field should display masked characters\n    StepKeyword.AND the actual password text should not be visible\n\n  @ui @edge-case\n  Scenario: Login button is disabled until both fields are filled\n    StepKeyword.GIVEN I am on the login page\n    StepKeyword.THEN the login button should be disabled\n    StepKeyword.WHEN I enter \"user@example.com\" in the email field\n    StepKeyword.THEN the login button should still be disabled\n    StepKeyword.WHEN I enter \"Password123\" in the password field\n    StepKeyword.THEN the login button should be enabled"
}