{
  "id": "report_20251203_081208",
  "project_id": "ce1a8cc0-da85-48e2-b349-7bf9311e023f",
  "project_name": "Alliant Insurance",
  "executed_at": "2025-12-03T08:12:08.510690",
  "total_tests": 1,
  "passed": 0,
  "failed": 1,
  "skipped": 0,
  "duration": 71.489152,
  "results": [
    {
      "test_case_id": "feature_1764066099.460405_Successfully_save_tile_configuration_changes",
      "test_case_name": "Successfully save tile configuration changes",
      "status": "failed",
      "duration": 66.713,
      "error_message": "Step 1: Unknown action: gherkin_step",
      "screenshot_path": "data\\agent_knowledge\\screenshots\\feature_1764066099.460405_Successfully_save_tile_configuration_changes_step1_failure.png",
      "logs": [
        "Step 1: step - failed",
        "Step 2: Noop - passed",
        "Step 3: step - failed",
        "Step 4: step - failed",
        "Step 5: Click on 'save button' - failed",
        "Step 6: Assert on 'a success confirmation message' - failed",
        "Step 7: step - failed",
        "Step 8: step - failed"
      ]
    }
  ],
  "format": "gherkin",
  "execution_mode": "autonomous",
  "pass_rate": 0.0,
  "total_ai_calls": 0,
  "total_kb_hits": 8,
  "ai_dependency_percent": 0.0,
  "new_selectors_learned": 0,
  "errors": []
}